jsonbp/__init__.py
jsonbp/array.py
jsonbp/blueprint.py
jsonbp/declaration.py
jsonbp/error.py
jsonbp/exception.py
jsonbp/field.py
jsonbp/loader.py
jsonbp/parser.py
jsonbp/types.py
jsonbp/localization/en_US.ini
jsonbp/localization/pt_BR.ini
jsonbp-1.2.1.dist-info/licenses/LICENSE.txt
jsonbp-1.2.1.dist-info/METADATA
jsonbp-1.2.1.dist-info/WHEEL
jsonbp-1.2.1.dist-info/top_level.txt
jsonbp-1.2.1.dist-info/RECORD
