Metadata-Version: 2.4
Name: jsonbp
Version: 1.2.1
Summary: Schema based JSON Parser/Serializer
Author-email: Gustavo Venturini <gustavo.c.venturini@gmail.com>
License-Expression: BSD-3-Clause
Project-URL: Homepage, https://github.com/vottini/jsonbp
Project-URL: Documentation, https://jsonbp.readthedocs.io/en/stable/
Keywords: JSON,serialization,deserialization
Classifier: Development Status :: 5 - Production/Stable
Classifier: Intended Audience :: Developers
Classifier: Operating System :: OS Independent
Classifier: Programming Language :: Python :: 3 :: Only
Requires-Python: >=3.11
License-File: LICENSE.txt
Dynamic: license-file
